csbs_import/__init__.py
csbs_import/cli.py
csbs_import/generator.py
csbs_import/lib.py
csbs_import/models.py
csbs_import/templates/assemblies.py.jinja2
csbs_import/templates/assembly_tree.py.jinja2
csbs_import/templates/fake_instances.py.jinja2
csbs_import/templates/info.py.jinja2
csbs_import/templates/instances.py.jinja2
csbs_import/templates/mock.py.jinja2
csbs_import/version.py
as_csbs_import-3.10.1.dist-info/METADATA
as_csbs_import-3.10.1.dist-info/WHEEL
as_csbs_import-3.10.1.dist-info/entry_points.txt
as_csbs_import-3.10.1.dist-info/RECORD
