Metadata-Version: 2.1
Name: as-csbs-import
Version: 3.10.1
Summary: Convert CSBS information into Python code stubs.
License: Proprietary
Author: Clinton Roy
Author-email: clintonr@ansto.gov.au
Requires-Python: >=3.9,<4.0
Classifier: License :: Other/Proprietary License
Classifier: Programming Language :: Python :: 3
Classifier: Programming Language :: Python :: 3.9
Classifier: Programming Language :: Python :: 3.10
Classifier: Programming Language :: Python :: 3.11
Requires-Dist: Jinja2 (>=3.1.2,<4.0.0)
Requires-Dist: inflect (>=6.0.2,<7.0.0)
Requires-Dist: requests (>=2.28.2,<3.0.0)
Requires-Dist: requests-file (>=1.5.1,<2.0.0)
Requires-Dist: rfc3986 (>=2.0.0,<3.0.0)
Requires-Dist: tomli (>=2.0.1,<3.0.0) ; python_version < "3.11"
Requires-Dist: typer (>=0.7.0,<0.8.0)
